lunafind/__about__.py
lunafind/__init__.py
lunafind/__main__.py
lunafind/album.py
lunafind/attridict.py
lunafind/cli.py
lunafind/config.py
lunafind/filtering.py
lunafind/order.py
lunafind/post.py
lunafind/stream.py
lunafind/utils.py
lunafind/clients/__init__.py
lunafind/clients/auto.py
lunafind/clients/base.py
lunafind/clients/danbooru.py
lunafind/clients/local.py
lunafind/clients/net.py
lunafind/data/default_config.ini
lunafind-0.5.5.dist-info/COPYING
lunafind-0.5.5.dist-info/COPYING.LESSER
lunafind-0.5.5.dist-info/METADATA
lunafind-0.5.5.dist-info/WHEEL
lunafind-0.5.5.dist-info/entry_points.txt
lunafind-0.5.5.dist-info/top_level.txt
lunafind-0.5.5.dist-info/RECORD
